CHANGES.rst
MANIFEST.in
Makefile
README.rst
babel.cfg
setup.cfg
setup.py
baseframe/.DS_Store
baseframe/Makefile
baseframe/__init__.py
baseframe/__init__.pyc
baseframe/_version.py
baseframe/_version.pyc
baseframe/assets.py
baseframe/assets.pyc
baseframe/deprecated.py
baseframe/deprecated.pyc
baseframe/errors.py
baseframe/errors.pyc
baseframe/filters.py
baseframe/filters.pyc
baseframe/signals.py
baseframe/signals.pyc
baseframe/staticdata.py
baseframe/staticdata.pyc
baseframe/user.pyc
baseframe/views.py
baseframe/views.pyc
baseframe.egg-info/PKG-INFO
baseframe.egg-info/SOURCES.txt
baseframe.egg-info/dependency_links.txt
baseframe.egg-info/not-zip-safe
baseframe.egg-info/requires.txt
baseframe.egg-info/top_level.txt
baseframe/forms/__init__.py
baseframe/forms/__init__.pyc
baseframe/forms/auto.py
baseframe/forms/auto.pyc
baseframe/forms/fields.py
baseframe/forms/fields.pyc
baseframe/forms/filters.py
baseframe/forms/filters.pyc
baseframe/forms/form.py
baseframe/forms/form.pyc
baseframe/forms/parsleyjs.py
baseframe/forms/parsleyjs.pyc
baseframe/forms/patch_wtforms.py
baseframe/forms/patch_wtforms.pyc
baseframe/forms/sqlalchemy.py
baseframe/forms/sqlalchemy.pyc
baseframe/forms/validators.py
baseframe/forms/validators.pyc
baseframe/forms/widgets.py
baseframe/forms/widgets.pyc
baseframe/static/.DS_Store
baseframe/static/humans.txt
baseframe/static/robots.txt
baseframe/static/css/.DS_Store
baseframe/static/css/animate.css
baseframe/static/css/baseframe-bs3.css
baseframe/static/css/baseframe-firasans.css
baseframe/static/css/baseframe-footable.css
baseframe/static/css/baseframe.css
baseframe/static/css/bootstrap-multiselect.css
baseframe/static/css/bootstrap-social.css
baseframe/static/css/bootstrap.css
baseframe/static/css/chosen.css
baseframe/static/css/codemirror.css
baseframe/static/css/dropzone.css
baseframe/static/css/editor.css
baseframe/static/css/fontawesome-3.1.css
baseframe/static/css/fontawesome-4.4.css
baseframe/static/css/jQRangeSlider.css
baseframe/static/css/jquery-ui.css
baseframe/static/css/jquery.nouislider.min.css
baseframe/static/css/jquery.oembed.css
baseframe/static/css/jquery.timepicker.css
baseframe/static/css/networkbar.css
