Metadata-Version: 1.1
Name: baseframe
Version: 0.3.1
Summary: Baseframe for HasGeek projects
Home-page: https://github.com/hasgeek/baseframe
Author: Kiran Jonnalagadda
Author-email: kiran@hasgeek.com
License: UNKNOWN
Keywords: baseframe
Platform: UNKNOWN
Classifier: Programming Language :: Python
Classifier: Programming Language :: Python :: 2.7
Classifier: License :: OSI Approved :: BSD License
Classifier: Operating System :: OS Independent
Classifier: Intended Audience :: Developers
Classifier: Development Status :: 3 - Alpha
Classifier: Topic :: Software Development :: Libraries
